[
  {
    "id":              1,
    "name":            "Иван Иванов",
    "passport_number": "1234 45454545",
    "phone":           "+7 913 444 55 66"
  },
  {
    "id":              2,
    "name":            "Никитка Жданко",
    "passport_number": "1234 45454545",
    "phone":           "+7 913 444 55 66"
  },
  {
    "id":              3,
    "name":            "Ричард Петров",
    "passport_number": "1234 45454545",
    "phone":           "+7 913 444 55 66"
  },
  {
    "id":              4,
    "name":            "Данилка Евлампов",
    "passport_number": "1234 45454545",
    "phone":           "+7 913 444 55 66"
  },
  {
    "id":              5,
    "name":            "Игнат Себастьянов",
    "passport_number": "1234 45454545",
    "phone":           "+7 913 444 55 66"
  }
]